[{"note":"C6","delay":0},{"note":"C6","delay":0.3529},{"note":"D#5","delay":0.1765},{"note":"F5","delay":0.1765},{"note":"C6","delay":0.1765},{"note":"A#5","delay":0.3529},{"note":"G5","delay":0.3529},{"note":"F5","delay":0.3529},{"note":"F#5","delay":0.1765},{"note":"G5","delay":0.1765},{"note":"F#5","delay":0.1765},{"note":"G5","delay":0.1765},{"note":"C6","delay":0.1765},{"note":"C6","delay":0.3529},{"note":"D#5","delay":0.1765},{"note":"F5","delay":0.1765},{"note":"C6","delay":0.1765},{"note":"A#5","delay":0.3529},{"note":"G5","delay":0.3529},{"note":"F5","delay":0.3529},{"note":"F#5","delay":0.1765},{"note":"G5","delay":0.1765},{"note":"F#5","delay":0.1765},{"note":"G5","delay":0.1765},{"note":"C6","delay":0.1765},{"note":"C6","delay":0.1765},{"note":"A#5","delay":0.1765},{"note":"C6","delay":0.1765},{"note":"G5","delay":0.3529},{"note":"G5","delay":0.3529},{"note":"D5","delay":0.1765},{"note":"D5","delay":0.1765},{"note":"A#5","delay":0.1765},{"note":"C6","delay":0.1765},{"note":"C6","delay":0.3529},{"note":"C6","delay":0.1765},{"note":"C6","delay":0.1765},{"note":"C6","delay":0.1765},{"note":"C6","delay":0.3529},{"note":"D#5","delay":0.1765},{"note":"F5","delay":0.1765},{"note":"C6","delay":0.1765},{"note":"A#5","delay":0.3529},{"note":"G5","delay":0.3529},{"note":"F5","delay":0.3529},{"note":"F#5","delay":0.1765},{"note":"G5","delay":0.1765},{"note":"F#5","delay":0.1765},{"note":"G5","delay":0.1765},{"note":"C6","delay":0.1765},{"note":"C6","delay":0.3529},{"note":"D#5","delay":0.1765},{"note":"F5","delay":0.1765},{"note":"C6","delay":0.1765},{"note":"A#5","delay":0.3529},{"note":"G5","delay":0.3529},{"note":"F5","delay":0.3529},{"note":"F#5","delay":0.1765},{"note":"G5","delay":0.1765},{"note":"F#5","delay":0.1765},{"note":"G5","delay":0.1765},{"note":"C6","delay":0.1765},{"note":"C6","delay":0.1765},{"note":"A#5","delay":0.1765},{"note":"C6","delay":0.1765},{"note":"G5","delay":0.3529},{"note":"G5","delay":0.3529},{"note":"D5","delay":0.1765},{"note":"D5","delay":0.1765},{"note":"A#5","delay":0.1765},{"note":"C6","delay":0.1765}]